holistictraceanalysis-0.5.0.dist-info/licenses/LICENSE
hta/__init__.py
hta/memory_analysis.py
hta/trace_analysis.py
hta/trace_diff.py
hta/version.py
hta/analyzers/__init__.py
hta/analyzers/breakdown_analysis.py
hta/analyzers/communication_analysis.py
hta/analyzers/critical_path_analysis.py
hta/analyzers/cuda_kernel_analysis.py
hta/analyzers/cupti_counter_analysis.py
hta/analyzers/straggler.py
hta/analyzers/straggler_analysis.py
hta/analyzers/timeline.py
hta/analyzers/trace_counters.py
hta/common/__init__.py
hta/common/call_stack.py
hta/common/constants.py
hta/common/execution_trace.py
hta/common/timeline.py
hta/common/trace.py
hta/common/trace_call_graph.py
hta/common/trace_call_stack.py
hta/common/trace_df.py
hta/common/trace_file.py
hta/common/trace_filter.py
hta/common/trace_parser.py
hta/common/trace_stack_filter.py
hta/common/trace_symbol_table.py
hta/common/types.py
hta/configs/__init__.py
hta/configs/config.py
hta/configs/default_event_args.py
hta/configs/default_values.py
hta/configs/env_options.py
hta/configs/event_args_yaml_parser.py
hta/configs/logging.config
hta/configs/parser_config.py
hta/configs/trace_analyzer.json
hta/utils/__init__.py
hta/utils/checker.py
hta/utils/test_utils.py
hta/utils/utils.py
hta/utils/validate_trace.py
param_bench/et_replay/__init__.py
param_bench/et_replay/et_replay_utils.py
param_bench/et_replay/execution_trace.py
param_bench/et_replay/utils.py
param_bench/et_replay/comm/commsTraceParser.py
param_bench/et_replay/comm/comms_utils.py
param_bench/et_replay/comm/param_profile.py
param_bench/et_replay/comm/pytorch_backend_utils.py
param_bench/et_replay/comm/pytorch_dist_backend.py
param_bench/et_replay/comm/pytorch_tpu_backend.py
param_bench/et_replay/tests/test_execution_trace.py
param_bench/et_replay/tests/inputs/__init__.py
param_bench/et_replay/tools/comm_replay.py
param_bench/et_replay/tools/et_replay.py
param_bench/et_replay/tools/validate_trace.py
param_bench/inference/compute/pt/pytorch_linear.py
param_bench/train/comms/pt/comms.py
holistictraceanalysis-0.5.0.dist-info/METADATA
holistictraceanalysis-0.5.0.dist-info/WHEEL
holistictraceanalysis-0.5.0.dist-info/top_level.txt
holistictraceanalysis-0.5.0.dist-info/RECORD
